azure/ai/formrecognizer/__init__.py
azure/ai/formrecognizer/_api_versions.py
azure/ai/formrecognizer/_document_analysis_client.py
azure/ai/formrecognizer/_document_model_administration_client.py
azure/ai/formrecognizer/_form_base_client.py
azure/ai/formrecognizer/_form_recognizer_client.py
azure/ai/formrecognizer/_form_training_client.py
azure/ai/formrecognizer/_helpers.py
azure/ai/formrecognizer/_models.py
azure/ai/formrecognizer/_polling.py
azure/ai/formrecognizer/_response_handlers.py
azure/ai/formrecognizer/_user_agent.py
azure/ai/formrecognizer/_version.py
azure/ai/formrecognizer/py.typed
azure/ai/formrecognizer/_generated/__init__.py
azure/ai/formrecognizer/_generated/_configuration.py
azure/ai/formrecognizer/_generated/_form_recognizer_client.py
azure/ai/formrecognizer/_generated/_operations_mixin.py
azure/ai/formrecognizer/_generated/_version.py
azure/ai/formrecognizer/_generated/models.py
azure/ai/formrecognizer/_generated/py.typed
azure/ai/formrecognizer/_generated/aio/__init__.py
azure/ai/formrecognizer/_generated/aio/_configuration.py
azure/ai/formrecognizer/_generated/aio/_form_recognizer_client.py
azure/ai/formrecognizer/_generated/aio/_operations_mixin.py
azure/ai/formrecognizer/_generated/v2022_08_31/__init__.py
azure/ai/formrecognizer/_generated/v2022_08_31/_configuration.py
azure/ai/formrecognizer/_generated/v2022_08_31/_form_recognizer_client.py
azure/ai/formrecognizer/_generated/v2022_08_31/_patch.py
azure/ai/formrecognizer/_generated/v2022_08_31/_vendor.py
azure/ai/formrecognizer/_generated/v2022_08_31/py.typed
azure/ai/formrecognizer/_generated/v2022_08_31/aio/__init__.py
azure/ai/formrecognizer/_generated/v2022_08_31/aio/_configuration.py
azure/ai/formrecognizer/_generated/v2022_08_31/aio/_form_recognizer_client.py
azure/ai/formrecognizer/_generated/v2022_08_31/aio/_patch.py
azure/ai/formrecognizer/_generated/v2022_08_31/aio/_vendor.py
azure/ai/formrecognizer/_generated/v2022_08_31/aio/operations/__init__.py
azure_ai_formrecognizer-3.3.3.dist-info/LICENSE
azure_ai_formrecognizer-3.3.3.dist-info/METADATA
azure_ai_formrecognizer-3.3.3.dist-info/WHEEL
azure_ai_formrecognizer-3.3.3.dist-info/top_level.txt
azure_ai_formrecognizer-3.3.3.dist-info/RECORD
