Metadata-Version: 2.1
Name: azure-ai-formrecognizer
Version: 3.3.3
Summary: Microsoft Azure Form Recognizer Client Library for Python
Home-page: https://github.com/Azure/azure-sdk-for-python
Author: Microsoft Corporation
Author-email: azpysdkhelp@microsoft.com
License: MIT License
Keywords: azure,form recognizer,cognitive services,document analyzer,document analysis,applied ai,azure sdk
Classifier: Development Status :: 5 - Production/Stable
Classifier: Programming Language :: Python
Classifier: Programming Language :: Python :: 3 :: Only
Classifier: Programming Language :: Python :: 3
Classifier: Programming Language :: Python :: 3.8
Classifier: Programming Language :: Python :: 3.9
Classifier: Programming Language :: Python :: 3.10
Classifier: Programming Language :: Python :: 3.11
Classifier: Programming Language :: Python :: 3.12
Classifier: License :: OSI Approved :: MIT License
Requires-Python: >=3.8
License-File: LICENSE
Requires-Dist: azure-core>=1.23.0
Requires-Dist: msrest>=0.6.21
Requires-Dist: azure-common>=1.1
Requires-Dist: typing-extensions>=4.0.1
